README.rst
django_basic_auth.py
setup.py
django_basic_authentication_decorator.egg-info/PKG-INFO
django_basic_authentication_decorator.egg-info/SOURCES.txt
django_basic_authentication_decorator.egg-info/dependency_links.txt
django_basic_authentication_decorator.egg-info/top_level.txt