Metadata-Version: 1.0
Name: django-basic-authentication-decorator
Version: 0.9
Summary: Decorator to provide Basic Authentication for Django Views
Home-page: https://github.com/m7v8/django-basic-authentication-decorator
Author: UNKNOWN
Author-email: UNKNOWN
License: BSD
Platform: UNKNOWN
